graphs_graph_sweldeha/__init__.py
graphs_graph_sweldeha/heapq.py
graphs_graph_sweldeha/mod.py
graphs_graph_sweldeha/sp.py
graphs_graph_sweldeha-0.0.1.dist-info/METADATA
graphs_graph_sweldeha-0.0.1.dist-info/WHEEL
graphs_graph_sweldeha-0.0.1.dist-info/RECORD
