Metadata-Version: 2.3
Name: graphs_graph_sweldeha
Version: 0.0.1
Summary: A Python package for Dijkstra's shortest path algorithm using a graph.
Project-URL: Homepage, https://github.com/samrawitw/graph_sweldeha
Project-URL: Bug Tracker, https://github.com/samrawitw/graph_sweldeha/issues
Author-email: Samrawit Weldehawariyat <samrawitwolde8@gmail.com>
Classifier: License :: OSI Approved :: MIT License
Classifier: Operating System :: OS Independent
Classifier: Programming Language :: Python :: 3
Requires-Python: >=3.7
